{
  "name": "破障行动",
  "description": "中央石墙阻断东西直通路线，重装单位可爆破开路；两翼分布补给站、前线基地和维修站三种据点，考验多兵种协同与地形改造能力",
  "grid": "hex",
  "orientation": "pointy",
  "radius": 8,
  "terrainCells": [
    { "q": -5, "r": -3, "terrain": "water" },
    { "q": -4, "r": -4, "terrain": "water" },
    { "q": -3, "r": -5, "terrain": "water" },
    { "q": 3, "r": 5, "terrain": "water" },
    { "q": 4, "r": 4, "terrain": "water" },
    { "q": 5, "r": 3, "terrain": "water" },
    { "q": -3, "r": 3, "terrain": "water" },
    { "q": 3, "r": -3, "terrain": "water" },
    { "q": 0, "r": -3, "terrain": "blocker" },
    { "q": 0, "r": -2, "terrain": "blocker" },
    { "q": 0, "r": -1, "terrain": "blocker" },
    { "q": 0, "r": 0, "terrain": "blocker" },
    { "q": 0, "r": 1, "terrain": "blocker" },
    { "q": 0, "r": 2, "terrain": "blocker" },
    { "q": 0, "r": 3, "terrain": "blocker" },
    { "q": -1, "r": 0, "terrain": "blocker" },
    { "q": 1, "r": 0, "terrain": "blocker" },
    { "q": -1, "r": 1, "terrain": "blocker" },
    { "q": 1, "r": -1, "terrain": "blocker" },
    { "q": -2, "r": 0, "terrain": "blocker" },
    { "q": 2, "r": 0, "terrain": "blocker" }
  ],
  "controlPoints": [
    { "id": "cp_nw", "name": "西北补给站", "kind": "supply", "q": -4, "r": -3 },
    { "id": "cp_n", "name": "北部维修站", "kind": "repair", "q": 1, "r": -5 },
    { "id": "cp_ne", "name": "东北前线基地", "kind": "forward_base", "q": 5, "r": -3 },
    { "id": "cp_sw", "name": "西南前线基地", "kind": "forward_base", "q": -5, "r": 3 },
    { "id": "cp_se", "name": "东南维修站", "kind": "repair", "q": 4, "r": 3 }
  ],
  "headquarters": {
    "player_a": { "q": -8, "r": 0 },
    "player_b": { "q": 8, "r": 0 }
  },
  "startingUnits": [
    { "owner": "player_a", "type": "infantry", "q": -7, "r": 0 },
    { "owner": "player_a", "type": "scout", "q": -7, "r": -1 },
    { "owner": "player_a", "type": "heavy", "q": -6, "r": 0 },
    { "owner": "player_a", "type": "ranger", "q": -7, "r": 1 },
    { "owner": "player_a", "type": "support", "q": -6, "r": -1 },
    { "owner": "player_b", "type": "infantry", "q": 7, "r": 0 },
    { "owner": "player_b", "type": "scout", "q": 7, "r": 1 },
    { "owner": "player_b", "type": "heavy", "q": 6, "r": 0 },
    { "owner": "player_b", "type": "ranger", "q": 7, "r": -1 },
    { "owner": "player_b", "type": "support", "q": 6, "r": 1 }
  ],
  "units": {
    "infantry": {
      "hp": 100,
      "attack": 30,
      "defense": 8,
      "moveRange": 3,
      "attackRange": 1,
      "cost": 45,
      "canCapture": true
    },
    "scout": {
      "hp": 65,
      "attack": 16,
      "defense": 4,
      "moveRange": 5,
      "attackRange": 1,
      "cost": 38,
      "canCapture": true
    },
    "heavy": {
      "hp": 150,
      "attack": 38,
      "defense": 13,
      "moveRange": 2,
      "attackRange": 1,
      "cost": 92,
      "canCapture": false
    },
    "ranger": {
      "hp": 72,
      "attack": 44,
      "defense": 3,
      "moveRange": 2,
      "attackRange": 3,
      "cost": 78,
      "canCapture": false
    },
    "support": {
      "hp": 82,
      "attack": 10,
      "defense": 5,
      "moveRange": 3,
      "attackRange": 1,
      "cost": 60,
      "canCapture": false,
      "healPower": 22
    }
  },
  "headquartersSpec": {
    "hp": 180,
    "defense": 6
  },
  "balance": {
    "startingSupplies": 208,
    "baseIncome": 10,
    "controlPointIncome": 8,
    "damageVarianceRange": 3,
    "minimumDamage": 1,
    "healVarianceRange": 6,
    "actionsPerTurn": 5,
    "maxTurns": 15,
    "adjudicationWeights": {
      "enemyHqDamage": 4,
      "ownHqHp": 2,
      "controlPoint": 90,
      "armyValue": 2,
      "supplies": 1
    },
    "controlPointTypes": {
      "supply": { "income": 12, "deployDiscount": 0, "repairAmount": 0 },
      "forward_base": { "income": 8, "deployDiscount": 8, "repairAmount": 0 },
      "repair": { "income": 8, "deployDiscount": 0, "repairAmount": 10 }
    }
  }
}
